dcnv2_ext.cpython-39-x86_64-linux-gnu.so
nms.cpython-39-x86_64-linux-gnu.so
mmkg_stvg_bert/__init__.py
mmkg_stvg_bert/app.py
mmkg_stvg_bert/demo.py
mmkg_stvg_bert/logger.py
mmkg_stvg_bert/opts.py
mmkg_stvg_bert/DCNv2/__init__.py
mmkg_stvg_bert/DCNv2/dcn_v2.py
mmkg_stvg_bert/DCNv2/dcn_v2_onnx.py
mmkg_stvg_bert/DCNv2/setup.py
mmkg_stvg_bert/DCNv2/testcpu.py
mmkg_stvg_bert/DCNv2/testcuda.py
mmkg_stvg_bert/detectors/__init__.py
mmkg_stvg_bert/detectors/base_detector.py
mmkg_stvg_bert/detectors/ctdet.py
mmkg_stvg_bert/detectors/ddd.py
mmkg_stvg_bert/detectors/detector_factory.py
mmkg_stvg_bert/detectors/exdet.py
mmkg_stvg_bert/detectors/multi_pose.py
mmkg_stvg_bert/models/__init__.py
mmkg_stvg_bert/models/data_parallel.py
mmkg_stvg_bert/models/decode.py
mmkg_stvg_bert/models/losses.py
mmkg_stvg_bert/models/model.py
mmkg_stvg_bert/models/scatter_gather.py
mmkg_stvg_bert/models/utils.py
mmkg_stvg_bert/models/networks/__init__.py
mmkg_stvg_bert/models/networks/dlav0.py
mmkg_stvg_bert/models/networks/lang_feats.py
mmkg_stvg_bert/models/networks/large_hourglass.py
mmkg_stvg_bert/models/networks/msra_resnet.py
mmkg_stvg_bert/models/networks/pose_dla_dcn.py
mmkg_stvg_bert/models/networks/resnet_dcn.py
mmkg_stvg_bert/models/networks/resnet_dcn_1.py
mmkg_stvg_bert/models/networks/resnet_dcn_2.py
mmkg_stvg_bert/models/networks/utils.py
mmkg_stvg_bert/models/networks/vilbert.py
mmkg_stvg_bert/models/networks/vilbert2.py
mmkg_stvg_bert/models/networks/vilbert3.py
mmkg_stvg_bert/models/networks/vilbert4.py
mmkg_stvg_bert/models/networks/vilbert5.py
mmkg_stvg_bert/trains/__init__.py
mmkg_stvg_bert/trains/base_trainer.py
mmkg_stvg_bert/trains/ctdet.py
mmkg_stvg_bert/trains/ddd.py
mmkg_stvg_bert/trains/exdet.py
mmkg_stvg_bert/trains/multi_pose.py
mmkg_stvg_bert/trains/train_factory.py
mmkg_stvg_bert/utils/__init__.py
mmkg_stvg_bert/utils/ddd_utils.py
mmkg_stvg_bert/utils/debugger.py
mmkg_stvg_bert/utils/image.py
mmkg_stvg_bert/utils/oracle_utils.py
mmkg_stvg_bert/utils/post_process.py
mmkg_stvg_bert-0.1.0.dist-info/METADATA
mmkg_stvg_bert-0.1.0.dist-info/WHEEL
mmkg_stvg_bert-0.1.0.dist-info/top_level.txt
mmkg_stvg_bert-0.1.0.dist-info/RECORD
