Metadata-Version: 2.1
Name: mmkg-stvg-bert
Version: 0.1.0
Summary: MMKG Models
Home-page: https://github.com/cjeen/mmkg-stvg-bert
Download-URL: https://github.com/cjeen/mmkg-stvg-bert/tags
Author: Chenjian Gao
Author-email: gaochenjian@buaa.edu.cn
Requires-Python: >=3.9
Requires-Dist: opencv-python
Requires-Dist: aiofiles
Requires-Dist: fastapi
Requires-Dist: uvicorn[standard]
Requires-Dist: python-multipart
Requires-Dist: progress
Requires-Dist: boto3
Requires-Dist: tqdm
Requires-Dist: tensorboardX
Requires-Dist: Cython
